pyipcmini/__init__.py
pyipcmini/usb_ion_pump.py
pyipcmini/version.py
pyipcmini/functions/__init__.py
pyipcmini/functions/ion_pump.py
pyipcmini/functions/ion_pump_base_functions.py
pyipcmini/functions/ion_pump_dic.py
pyipcmini/functions/ion_pump_read_functions.py
pyipcmini/functions/ion_pump_set_functions.py
pyipcmini/scripts/__init__.py
pyipcmini/scripts/single_measurement.py
pyIPCMini-0.1.0.dist-info/LICENSE
pyIPCMini-0.1.0.dist-info/METADATA
pyIPCMini-0.1.0.dist-info/WHEEL
pyIPCMini-0.1.0.dist-info/entry_points.txt
pyIPCMini-0.1.0.dist-info/top_level.txt
pyIPCMini-0.1.0.dist-info/RECORD
