Metadata-Version: 2.1
Name: pyIPCMini
Version: 0.1.0
Summary: pyIPCMini is a package to communicate and control via USB/serial the ion pump controller type IPCMini from Agilent.
Author-email: Benjamin Pasquiou <benjamin.pasquiou@univ-paris13.fr>
Project-URL: Homepage, https://github.com/benjaminpasquiou/pyIPCMini
Project-URL: Documentation, https://pyIPCMini.readthedocs.io
Project-URL: Repository, https://github.com/benjaminpasquiou/pyIPCMini.git
Project-URL: Issues, https://github.com/benjaminpasquiou/pyIPCMini/issues
Project-URL: Changelog, https://github.com/benjaminpasquiou/pyIPCMini/blob/main/CHANGELOG.md
Keywords: IPCMini,driver,ion pump
Classifier: Development Status :: 3 - Alpha
Classifier: Intended Audience :: Science/Research
Classifier: License :: OSI Approved :: BSD License
Classifier: Programming Language :: Python :: 3
Classifier: Programming Language :: Python :: 3 :: Only
Classifier: Programming Language :: Python :: 3.7
Classifier: Programming Language :: Python :: 3.8
Classifier: Programming Language :: Python :: 3.9
Classifier: Programming Language :: Python :: 3.10
Classifier: Programming Language :: Python :: 3.11
Classifier: Programming Language :: Python :: 3.12
Classifier: Programming Language :: Python :: 3.13
Classifier: Programming Language :: Python :: 3.14
Classifier: Topic :: Scientific/Engineering
Classifier: Topic :: System :: Hardware :: Hardware Drivers
Classifier: Typing :: Typed
Classifier: Operating System :: Microsoft :: Windows
Classifier: Operating System :: Unix
Classifier: Operating System :: MacOS
Requires-Python: >=3.7
License-File: LICENSE
Requires-Dist: pyserial
Requires-Dist: python-dateutil
